src/__init__.py
src/constants/__init__.py
src/constants/urls.py
src/dagster/__init__.py
src/dagster/assets.py
src/dagster/definitions.py
src/dagster/jobs.py
src/dagster/schedulers.py
src/dagster_test/__init__.py
src/pipelines/__init__.py
src/pipelines/hubspot.py
dl_pipeline_connector-0.1.0.dist-info/METADATA
dl_pipeline_connector-0.1.0.dist-info/WHEEL
dl_pipeline_connector-0.1.0.dist-info/RECORD
