Metadata-Version: 2.4
Name: dl-pipeline-connector
Version: 0.1.0
Summary: HubSpot to BigQuery ETL pipeline using dlt and Dagster
Project-URL: Homepage, https://github.com/datumlabsio/dl-pipeline-connector
Project-URL: Repository, https://github.com/datumlabsio/dl-pipeline-connector
Project-URL: Documentation, https://github.com/datumlabsio/dl-pipeline-connector#readme
Project-URL: Issues, https://github.com/datumlabsio/dl-pipeline-connector/issues
Author-email: Saqib <saqibashraf268@gmail.com>
License: MIT
Keywords: bigquery,dagster,data-pipeline,dlt,etl,hubspot
Classifier: Development Status :: 3 - Alpha
Classifier: Intended Audience :: Developers
Classifier: Programming Language :: Python :: 3
Classifier: Programming Language :: Python :: 3.10
Classifier: Programming Language :: Python :: 3.11
Classifier: Programming Language :: Python :: 3.12
Classifier: Topic :: Database
Classifier: Topic :: Software Development :: Libraries :: Python Modules
Requires-Python: >=3.10
Requires-Dist: dagster
Requires-Dist: dagster-embedded-elt
Requires-Dist: dagster-slack
Requires-Dist: dagster-webserver
Requires-Dist: dlt[bigquery]
Requires-Dist: python-dotenv
Requires-Dist: requests
Provides-Extra: dev
Requires-Dist: mypy>=1.0.0; extra == 'dev'
Requires-Dist: pytest-cov>=4.0.0; extra == 'dev'
Requires-Dist: pytest>=7.0.0; extra == 'dev'
Requires-Dist: ruff>=0.1.0; extra == 'dev'
